Simulation/Verilog/LogicCircuits/ALU/salu/salu.v
//Simple ALU
//`timescale 1ns/100ps
module salu(operanda,operandb,mux,result);
    
    //inputs,outputs and wires
    input [7:0] operanda,operandb;
    input [2:0] mux;
    output [7:0] result;
    wire [7:0] op1,op2;
    reg [7:0] r;
    
    //variables for operations
    assign op1 = operanda;
    assign op2 = operandb;
    //Assign the output 
    assign result = r;

    always @(mux or op1 or op2)
    begin
        case (mux)
         0 : r = op1 + op2;    //Add
         1 : r = op1 - op2;    //Sub
         2 : r = ~op1;         //NOT
         3 : r = op1 & op2;    //AND
         4 : r = op1 | op2;    //OR
         5 : r = ~(op1 & op2); //NAND 
         6 : r = ~(op1 | op2); //NOR                
         7 : r = op1 ^ op2;    //XOR
        endcase 
    end
    
endmodule

Simulation/Verilog/LogicCircuits/ALU/salu/salu_tb.v
module salu_tb;

    // Inputs
    reg [7:0] opA;
    reg [7:0] opB;
    reg [2:0] Mux;

    // Outputs
    wire [7:0] Result;

    // testing salu
    salu SALU ( .operanda(opA), .operandb(opB), .mux(Mux), .result(Result));

    initial begin
      $dumpfile("wave.vcd");
      $dumpvars(); 
      $monitor("simtime=%g,opA=%b,opB=%b,Mux=%b,Result=%b",$time,opA,opB,Mux,Result);
      // Apply inputs.
        opA = 8'b01101010;
        opB = 8'b00111011;
        // Multiplex
        Mux = 0; #10;
        Mux = 1; #10;
        Mux = 2; #10;
        Mux = 3; #10;
        Mux = 4; #10;
        Mux = 5; #10;
        Mux = 6; #10;
        Mux = 7; #10;
        //#10 $finish;
    end
      
endmodule

Simulation/Verilog/LogicCircuits/ALU/salu/wave.vcd
$date
	Sat May 14 23:37:59 2022
$end
$version
	Icarus Verilog
$end
$timescale
	1s
$end
$scope module salu_tb $end
$var wire 8 ! Result [7:0] $end
$var reg 3 " Mux [2:0] $end
$var reg 8 # opA [7:0] $end
$var reg 8 $ opB [7:0] $end
$scope module SALU $end
$var wire 3 % mux [2:0] $end
$var wire 8 & op1 [7:0] $end
$var wire 8 ' op2 [7:0] $end
$var wire 8 ( operanda [7:0] $end
$var wire 8 ) operandb [7:0] $end
$var wire 8 * result [7:0] $end
$var reg 8 + r [7:0] $end
$upscope $end
$upscope $end
$enddefinitions $end
#0
$dumpvars
b10100101 +
b10100101 *
b111011 )
b1101010 (
b111011 '
b1101010 &
b0 %
b111011 $
b1101010 #
b0 "
b10100101 !
$end
#10
b101111 !
b101111 *
b101111 +
b1 "
b1 %
#20
b10010101 !
b10010101 *
b10010101 +
b10 "
b10 %
#30
b101010 !
b101010 *
b101010 +
b11 "
b11 %
#40
b1111011 !
b1111011 *
b1111011 +
b100 "
b100 %
#50
b11010101 !
b11010101 *
b11010101 +
b101 "
b101 %
#60
b10000100 !
b10000100 *
b10000100 +
b110 "
b110 %
#70
b1010001 !
b1010001 *
b1010001 +
b111 "
b111 %
